README.md
setup.py
bmaquet_tap_pagerduty.egg-info/PKG-INFO
bmaquet_tap_pagerduty.egg-info/SOURCES.txt
bmaquet_tap_pagerduty.egg-info/dependency_links.txt
bmaquet_tap_pagerduty.egg-info/entry_points.txt
bmaquet_tap_pagerduty.egg-info/requires.txt
bmaquet_tap_pagerduty.egg-info/top_level.txt
tap_pagerduty/__init__.py
tap_pagerduty/streams.py
tap_pagerduty/schemas/incidents.json
tap_pagerduty/schemas/notifications.json
tap_pagerduty/schemas/services.json