Metadata-Version: 2.1
Name: bmaquet-tap-pagerduty
Version: 1.0.1
Summary: Singer.io tap for extracting data from Pagerduty v2 API
Home-page: https://github.com/BenjMaq/bmaquet-tap-pagerduty
License: GPLv3
Keywords: singer tap python pagerduty
Platform: UNKNOWN
Classifier: License :: OSI Approved :: GNU General Public License v3 (GPLv3)
Classifier: Natural Language :: English
Classifier: Topic :: Software Development
Classifier: Intended Audience :: Developers
Classifier: Operating System :: OS Independent
Classifier: Programming Language :: Python :: 3 :: Only
Classifier: Programming Language :: Python :: 3.6
Classifier: Programming Language :: Python :: 3.7
Requires-Python: >=3.6
Provides-Extra: dev
